src/__init__.py
Topsis_Prachi_102003018-0.0.2.dist-info/LICENSE
Topsis_Prachi_102003018-0.0.2.dist-info/METADATA
Topsis_Prachi_102003018-0.0.2.dist-info/WHEEL
Topsis_Prachi_102003018-0.0.2.dist-info/top_level.txt
Topsis_Prachi_102003018-0.0.2.dist-info/RECORD
