Metadata-Version: 2.1
Name: Topsis-Prachi-102003018
Version: 0.0.2
Summary: command line tool for calculating topsis score
Home-page: UNKNOWN
Author: Prachi Gupta
Author-email: pr.gupta059@gmail.com
License: UNKNOWN
Keywords: topsis
Platform: UNKNOWN
Classifier: Programming Language :: Python :: 3
Classifier: License :: OSI Approved :: MIT License
Classifier: Operating System :: OS Independent
License-File: LICENSE
Requires-Dist: pandas
